[
  {
    "fitScore": 5,
    "tier": "TIER 1",
    "firm": "India Sotheby's International Realty",
    "location": "Delhi NCR · est. 2014",
    "keyPerson": "Ashwin C. (CEO) + Amit Goyal (MD)",
    "title": "+ 7 directors incl. Sales Director",
    "phone": "Via enrichment",
    "email": "",
    "linkedin": "",
    "instagram": "@indiasothebysrealty",
    "website": "indiasothebysrealty",
    "luxuryEvidence": "MD publicly quoted on Camellias pricing; director portfolios list Camellias, Magnolias, Aralias & Lutyens' Delhi",
    "source": "A+W"
  },
  {
    "fitScore": 5,
    "tier": "TIER 1",
    "firm": "Vaastvik Realtors",
    "location": "Gurgaon · founder-led",
    "keyPerson": "Vivek Yadav",
    "title": "Founder",
    "phone": "Via website",
    "email": "",
    "linkedin": "",
    "instagram": "—",
    "website": "vaastvikrealtors.com",
    "luxuryEvidence": "Founder-led luxury advisory; cites ₹190 Cr Camellias penthouse record & unlisted DLF inventory access",
    "source": "W"
  },
  {
    "fitScore": 5,
    "tier": "TIER 1",
    "firm": "Rathi Global Realty Services",
    "location": "Gurgaon · est. 2005",
    "keyPerson": "TBD (enrichment)",
    "title": "—",
    "phone": "+91 77970 09700",
    "email": "",
    "linkedin": "",
    "instagram": "@rathirealtyofficial",
    "website": "rathiglobalrealty.com",
    "luxuryEvidence": "Dedicated DLF Camellias sales page on own website; 180% headcount growth YoY",
    "source": "A+W"
  },
  {
    "fitScore": 5,
    "tier": "TIER 1",
    "firm": "Wealthway Luxury",
    "location": "Gurgaon",
    "keyPerson": "TBD (web outreach)",
    "title": "—",
    "phone": "Via website",
    "email": "",
    "linkedin": "",
    "instagram": "—",
    "website": "wealthwayluxury.com",
    "luxuryEvidence": "Camellias inventory ₹85–200 Cr with dedicated NRI desk, FEMA-compliant investor support",
    "source": "W"
  },
  {
    "fitScore": 5,
    "tier": "TIER 1",
    "firm": "Oak N Stone Inc.",
    "location": "Gurgaon",
    "keyPerson": "TBD (web outreach)",
    "title": "—",
    "phone": "Via website",
    "email": "",
    "linkedin": "",
    "instagram": "—",
    "website": "oaknstoneinc.com",
    "luxuryEvidence": "Authorized broker relationships: DLF Camellias, Whiteland ultra-luxury, M3M Golf Estate",
    "source": "W"
  },
  {
    "fitScore": 5,
    "tier": "TIER 1",
    "firm": "Winworld Realty",
    "location": "Gurgaon",
    "keyPerson": "TBD (web outreach)",
    "title": "—",
    "phone": "Via website",
    "email": "",
    "linkedin": "",
    "instagram": "—",
    "website": "winworldrealty.in",
    "luxuryEvidence": "Published coverage of ₹95 Cr Camellias transaction; ultra-luxury content focus",
    "source": "W"
  },
  {
    "fitScore": 5,
    "tier": "TIER 1",
    "firm": "White Collar Realty",
    "location": "Gurgaon",
    "keyPerson": "TBD (web outreach)",
    "title": "—",
    "phone": "Via website",
    "email": "",
    "linkedin": "",
    "instagram": "—",
    "website": "whitecollarrealty.com",
    "luxuryEvidence": "Active Camellias listing pages incl. Camellias 2 (₹55 Cr+, penthouses to 16,500 sq ft)",
    "source": "W"
  },
  {
    "fitScore": 4,
    "tier": "TIER 2",
    "firm": "Vero Estate",
    "location": "Gurgaon · est. 2022",
    "keyPerson": "Harneet M.",
    "title": "Founder",
    "phone": "+91 98992 42523",
    "email": "",
    "linkedin": "",
    "instagram": "—",
    "website": "vero.estate",
    "luxuryEvidence": "Self-branded 'Luxury Real Estate Firm'; boutique Golf Course Road positioning",
    "source": "A"
  },
  {
    "fitScore": 4,
    "tier": "TIER 2",
    "firm": "Melhor Group",
    "location": "Gurgaon · est. 1998",
    "keyPerson": "Dharwesh A. (MD) + Gaurav V.",
    "title": "MD / Founder + CP Development Mgr",
    "phone": "+91 95555 55550",
    "email": "",
    "linkedin": "",
    "instagram": "@melhorgroupofficial",
    "website": "melhorgroup.com",
    "luxuryEvidence": "Dedicated Channel Partner development function — strong partnership entry point",
    "source": "A"
  },
  {
    "fitScore": 4,
    "tier": "TIER 2",
    "firm": "STAR INDIA",
    "location": "Gurugram · est. 2002",
    "keyPerson": "TBD (enrichment)",
    "title": "—",
    "phone": "Via starindia.co",
    "email": "",
    "linkedin": "",
    "instagram": "—",
    "website": "starindia.co",
    "luxuryEvidence": "'Gurugram Luxury Real Estate' brand positioning; 75% growth over 24 months",
    "source": "A"
  },
  {
    "fitScore": 4,
    "tier": "TIER 2",
    "firm": "Luxury Homes (South Delhi)",
    "location": "South Delhi · est. 2000",
    "keyPerson": "TBD (enrichment)",
    "title": "—",
    "phone": "+91 99119 97266",
    "email": "",
    "linkedin": "",
    "instagram": "—",
    "website": "southdelhiprime.com",
    "luxuryEvidence": "South Delhi prime segment specialist — Lutyens-adjacent inventory",
    "source": "A"
  },
  {
    "fitScore": 4,
    "tier": "TIER 2",
    "firm": "InfraMantra",
    "location": "Gurgaon · est. 2017",
    "keyPerson": "Garvit T. + Shiwang S.",
    "title": "Co-Founders & Directors",
    "phone": "+91 86980 09900",
    "email": "",
    "linkedin": "",
    "instagram": "@inframantraofficial",
    "website": "inframantra.com",
    "luxuryEvidence": "Organised CP firm, ~90 staff; both co-founders reachable with verified emails",
    "source": "A"
  },
  {
    "fitScore": 4,
    "tier": "TIER 2",
    "firm": "Orion Realtors",
    "location": "Gurgaon · est. 2005",
    "keyPerson": "Mudit M. + Rajat M. + Sweta P.",
    "title": "Directors / Co-founders (4 DMs)",
    "phone": "Via orionrealtors.com",
    "email": "",
    "linkedin": "",
    "instagram": "@orionrealtorsgurgaon",
    "website": "orionrealtors.com",
    "luxuryEvidence": "Two-decade Gurgaon brokerage; four decision-makers mapped with emails",
    "source": "A"
  },
  {
    "fitScore": 4,
    "tier": "TIER 2",
    "firm": "City Space India",
    "location": "Gurgaon · est. 2010",
    "keyPerson": "Vikram G. (CEO) + Vikram J.",
    "title": "Founder-CEO / Director",
    "phone": "+91 73038 85715",
    "email": "",
    "linkedin": "",
    "instagram": "@cityspaceindiaofficial",
    "website": "cityspaceindia.com",
    "luxuryEvidence": "₹5.4M revenue brokerage; CEO + director both phone-verified in Apollo",
    "source": "A"
  },
  {
    "fitScore": 4,
    "tier": "TIER 2",
    "firm": "Asset Deals",
    "location": "Gurgaon · est. 2009",
    "keyPerson": "Vineet C. (CEO) + 2 Sales Directors",
    "title": "Founder-CEO",
    "phone": "+91 99538 41085",
    "email": "",
    "linkedin": "",
    "instagram": "—",
    "website": "assetdeals.in",
    "luxuryEvidence": "84% headcount growth YoY; full sales leadership mapped",
    "source": "A"
  },
  {
    "fitScore": 4,
    "tier": "TIER 2",
    "firm": "NYSA Luxury Homes",
    "location": "Gurgaon · est. 2023",
    "keyPerson": "Harry S.",
    "title": "CEO",
    "phone": "+91 99909 94222",
    "email": "",
    "linkedin": "",
    "instagram": "@nysaluxuryhomes",
    "website": "nysaluxuryhomes.com",
    "luxuryEvidence": "Luxury-branded boutique; CEO direct-phone flagged in Apollo",
    "source": "A"
  },
  {
    "fitScore": 4,
    "tier": "TIER 2",
    "firm": "NEELKANTH Luxury Homes",
    "location": "Gurgaon · est. 2011",
    "keyPerson": "Harlal B.",
    "title": "Director",
    "phone": "+91 99999 85711",
    "email": "",
    "linkedin": "",
    "instagram": "—",
    "website": "neelkanthluxuryhomes.com",
    "luxuryEvidence": "Luxury-branded boutique CP, 14-year track record",
    "source": "A"
  },
  {
    "fitScore": 3,
    "tier": "TIER 2",
    "firm": "ElitePRO Infra",
    "location": "Gurgaon · est. 2012",
    "keyPerson": "Amit C. (CEO) + Viren M.",
    "title": "CEO / Director",
    "phone": "+91 99686 86868",
    "email": "",
    "linkedin": "",
    "instagram": "—",
    "website": "eliteproinfra.com",
    "luxuryEvidence": "135-person organised brokerage; luxury share needs verification",
    "source": "A"
  },
  {
    "fitScore": 3,
    "tier": "TIER 2",
    "firm": "Lands and Spaces",
    "location": "Gurgaon · est. 2022",
    "keyPerson": "Ankur A.",
    "title": "Founder & MD",
    "phone": "+91 93557 19729",
    "email": "",
    "linkedin": "",
    "instagram": "@landsandspaces",
    "website": "landsandspaces.com",
    "luxuryEvidence": "Boutique, 150% growth in 6 months; founder email verified",
    "source": "A"
  },
  {
    "fitScore": 3,
    "tier": "TIER 2",
    "firm": "Torbit Realty",
    "location": "Gurgaon",
    "keyPerson": "Sanjeev K.",
    "title": "Founder, Author & CEO",
    "phone": "Via torbitrealty.com",
    "email": "",
    "linkedin": "",
    "instagram": "—",
    "website": "torbitrealty.com",
    "luxuryEvidence": "Industry-veteran founder; strong NCR network & media presence",
    "source": "A"
  },
  {
    "fitScore": 3,
    "tier": "TIER 2",
    "firm": "Prop-Keys Consulting",
    "location": "Gurgaon · est. 2022",
    "keyPerson": "Pramod S. + Vijender R.",
    "title": "Co-Founders",
    "phone": "Via prop-keys.com",
    "email": "",
    "linkedin": "",
    "instagram": "—",
    "website": "prop-keys.com",
    "luxuryEvidence": "Young CP firm, both co-founders mapped",
    "source": "A"
  },
  {
    "fitScore": 3,
    "tier": "TIER 2",
    "firm": "Propkarmaa",
    "location": "Noida · est. 2022",
    "keyPerson": "Harsh M.",
    "title": "Managing Director",
    "phone": "+91 99119 31000",
    "email": "",
    "linkedin": "",
    "instagram": "@propkarmaapvtltd",
    "website": "propkarmaa.com",
    "luxuryEvidence": "Noida-side coverage; MD email verified",
    "source": "A"
  },
  {
    "fitScore": 3,
    "tier": "TIER 2",
    "firm": "Urban Avenues",
    "location": "Gurgaon · est. 2014",
    "keyPerson": "Ankush A.",
    "title": "CEO",
    "phone": "+91 88007 70770",
    "email": "",
    "linkedin": "",
    "instagram": "—",
    "website": "urbanavenues.in",
    "luxuryEvidence": "Investment-advisory positioning for HNI buyers",
    "source": "A"
  },
  {
    "fitScore": 3,
    "tier": "TIER 2",
    "firm": "SeedWill Consulting",
    "location": "Gurgaon · est. 2018",
    "keyPerson": "Manav B.",
    "title": "Chief Executive Officer",
    "phone": "1800 123 1234",
    "email": "",
    "linkedin": "",
    "instagram": "—",
    "website": "seedwillconsulting.com",
    "luxuryEvidence": "~150-person consulting brokerage; mid-market lean, verify luxury book",
    "source": "A"
  },
  {
    "fitScore": 3,
    "tier": "TIER 2",
    "firm": "Propzilla",
    "location": "Gurgaon · est. 2015",
    "keyPerson": "TBD (enrichment)",
    "title": "—",
    "phone": "+91 98990 55030",
    "email": "",
    "linkedin": "",
    "instagram": "—",
    "website": "propzilla.in",
    "luxuryEvidence": "Established Gurgaon brokerage, 44% growth over 24 months",
    "source": "A"
  },
  {
    "fitScore": 3,
    "tier": "TIER 2",
    "firm": "Realty Smartz",
    "location": "Gurgaon · est. 2021",
    "keyPerson": "Amit A. (MD) + Chhavi M.",
    "title": "MD & Founder / Assoc. Director",
    "phone": "+91 80108 41841",
    "email": "",
    "linkedin": "",
    "instagram": "—",
    "website": "realtysmartz.in",
    "luxuryEvidence": "Appeared in 3 of 5 Apollo searches — strong keyword footprint",
    "source": "A"
  },
  {
    "fitScore": 3,
    "tier": "TIER 2",
    "firm": "Landmark GOC",
    "location": "Gurgaon",
    "keyPerson": "Rahul K.",
    "title": "Director",
    "phone": "+91 98100 26972",
    "email": "",
    "linkedin": "",
    "instagram": "—",
    "website": "landmarkgoc.com",
    "luxuryEvidence": "Organised CP firm, 47% growth over 24 months",
    "source": "A"
  }
]